functions_by_gregvalico/README.md
functions_by_gregvalico/math_functions.py
functions_by_gregvalico-0.3.0.dist-info/WHEEL
functions_by_gregvalico-0.3.0.dist-info/METADATA
functions_by_gregvalico-0.3.0.dist-info/RECORD
