Metadata-Version: 2.1
Name: functions-by-gregvalico
Version: 0.3.0
Summary: This is a test project.
Author: GregValico
Author-email: GregValico@gmail.com
Requires-Python: >=3.10,<4.0
Classifier: Programming Language :: Python :: 3
Classifier: Programming Language :: Python :: 3.10
Classifier: Programming Language :: Python :: 3.11
